Bachelor/AE/Verilog/Pow2/pow2.sv
module pow2(output z, input [7:0]x);

  assign
    #2 z=(~x[0]&~x[3]&~x[4]&~x[5]&~x[6]&~x[7]) | (~x[0]&~x[1]&~x[2]&~x[5]&~x[6]&~x[7])
      | (~x[0]&~x[1]&~x[2]&~x[3]&~x[4]&~x[7]) | (~x[1]&~x[2]&~x[3]&~x[4]&~x[5]&~x[6]);

endmodule

AE/Verilog/Pow2/test.v
module test();

reg [7:0] x;
wire z;
integer i;


pow2 mypow(z,x);

initial
  begin
    $dumpfile("test.vcd");
    $dumpvars;

    x[0]=0;
    x[1]=1;
    for (i=2;i<9;i++)
     begin
      x[i]=0;
     end

    #5
    x[6]=1;

    #5
    x[1]=0;

    #5
    x[7]=1;
      
    #5
    x[7]=0;
    x[0]=1;
    x[6]=0;    
 
    #5
    x[0]=0;
    #20 $finish;

  end
endmodule

Bachelor/AE/Verilog/Pow2/test.vcd
$date
	Tue Oct 29 19:39:28 2019
$end
$version
	Icarus Verilog
$end
$timescale
	1s
$end
$scope module test $end
$var wire 1 ! z $end
$var reg 8 " x [7:0] $end
$var integer 32 # i [31:0] $end
$scope module mypow $end
$var wire 8 $ x [7:0] $end
$var wire 1 ! z $end
$upscope $end
$upscope $end
$enddefinitions $end
#0
$dumpvars
b10 $
b1001 #
b10 "
x!
$end
#2
1!
#5
b1000010 "
b1000010 $
#7
0!
#10
b1000000 "
b1000000 $
#12
1!
#15
b11000000 "
b11000000 $
#17
0!
#20
b1 "
b1 $
#22
1!
#25
b0 "
b0 $
