AE/Verilog/mul4pipe/mul2.sv
module mul2 (output [N:0]z, input [N:0]x);
  parameter N=8;

  assign #2 z=x*2;
endmodule

Bachelor/AE/Verilog/mul4pipe/mul4.sv
module mul4(output [N:0]z, input [N:0]x, input clock);

  parameter N=8;

  wire [N:0] mul2int;
  wire [N:0] outreg;
  reg  [N:0] in;

  mul2 #(N) m1(mul2int,x);
  mul2 #(N) m2(z,mul2int);

  

endmodule // mul4

Bachelor/AE/Verilog/mul4pipe/test.v
module test ();

parameter N=6;

reg [N:0] x;
wire [N:0] z;
reg enable;
reg clock;

mul4 #(N) m4(z,x,clock);

always begin
  #1 clock=1;
  #2 clock=0;
end

initial begin
  $dumpfile("test.vcd");
  $dumpvars;
  enable=1;
  clock=0;
  x=2;
  #3
  x=4;
  #3
  x=8;
  #3
  $finish;
end

endmodule // test

Bachelor/AE/Verilog/mul4pipe/register.sv
module register(output reg [N:0] out, input [N:0] in, input clock);

parameter N=8;


always @ (posedge clock)
  begin
     out<=in;
  end


endmodule // registeoutput

Bachelor/AE/Verilog/mul4pipe/test.vcd
$date
	Thu Jan  2 20:45:09 2020
$end
$version
	Icarus Verilog
$end
$timescale
	1s
$end
$scope module register $end
$var wire 1 ! clock $end
$var wire 9 " in [8:0] $end
$var reg 9 # out [8:0] $end
$upscope $end
$scope module test $end
$var wire 7 $ z [6:0] $end
$var reg 1 % clock $end
$var reg 1 & enable $end
$var reg 7 ' x [6:0] $end
$scope module m4 $end
$var wire 1 % clock $end
$var wire 7 ( x [6:0] $end
$var wire 7 ) z [6:0] $end
$var wire 7 * mul2int [6:0] $end
$scope module m1 $end
$var wire 7 + x [6:0] $end
$var wire 7 , z [6:0] $end
$upscope $end
$scope module m2 $end
$var wire 7 - x [6:0] $end
$var wire 7 . z [6:0] $end
$upscope $end
$upscope $end
$upscope $end
$enddefinitions $end
#0
$dumpvars
bx .
bx -
bx ,
b10 +
bx *
bx )
b10 (
b10 '
1&
0%
bx $
bx #
bz "
z!
$end
#1
1%
#2
b100 *
b100 ,
b100 -
#3
0%
b100 '
b100 (
b100 +
#4
1%
b1000 $
b1000 )
b1000 .
#5
b1000 *
b1000 ,
b1000 -
#6
0%
b1000 '
b1000 (
b1000 +
#7
1%
b10000 $
b10000 )
b10000 .
#8
b10000 *
b10000 ,
b10000 -
